.gitignore
CHANGES.rst
MANIFEST.in
README.rst
bootstrap.py
buildout.cfg
develop.cfg
setup.py
sources.cfg
src/collective/__init__.py
src/collective.runhook.egg-info/PKG-INFO
src/collective.runhook.egg-info/SOURCES.txt
src/collective.runhook.egg-info/dependency_links.txt
src/collective.runhook.egg-info/entry_points.txt
src/collective.runhook.egg-info/namespace_packages.txt
src/collective.runhook.egg-info/not-zip-safe
src/collective.runhook.egg-info/requires.txt
src/collective.runhook.egg-info/top_level.txt
src/collective/runhook/__init__.py
src/collective/runhook/configure.zcml