Metadata-Version: 1.1
Name: collective.runhook
Version: 0.9.3
Summary: Named instance run script entry points for plone.recipe.zope2instance
Home-page: https://github.com/collective/collective.runhook/
Author: Asko Soukka
Author-email: asko.soukka@iki.fi
License: GPL
Platform: UNKNOWN
Classifier: Programming Language :: Python
